japyd-0.1.19.dist-info/METADATA
japyd-0.1.19.dist-info/WHEEL
japyd-0.1.19.dist-info/entry_points.txt
japyd-0.1.19.dist-info/licenses/LICENCE
japyd/__init__.py
japyd/client.py
japyd/dotnet.py
japyd/filter.py
japyd/jsonapi.py
japyd/models.py
japyd/utils.py
japyd-0.1.19.dist-info/RECORD
