Metadata-Version: 2.1
Name: japyd
Version: 0.1.19
Summary: Automate JSON:API relationships with Pydantic. No manual mapping, just clean code.
Author-Email: gdoumenc <gdoumenc@neorezo.io>
License: MIT
Requires-Python: >=3.11
Requires-Dist: flask
Requires-Dist: flask-pydantic>=0.13.1
Requires-Dist: twine
Provides-Extra: dev
Requires-Dist: pytest>=8.4.1; extra == "dev"
Requires-Dist: mypy>=1.17.1; extra == "dev"
Requires-Dist: ruff>=0.12.7; extra == "dev"
Requires-Dist: cloudsmith-cli>=1.8.3; extra == "dev"
Requires-Dist: codecov>=2.1.13; extra == "dev"
Requires-Dist: pytest-cov>=6.2.1; extra == "dev"
Requires-Dist: pip>=25.2; extra == "dev"
Requires-Dist: types-requests>=2.31.0.6; extra == "dev"
